[{"type":"TRAIT","text":"phase","intent":"","topic":"","traits":"","entities":""},{"type":"TRAIT","text":"bye","intent":"","topic":"","traits":"","entities":""},{"type":"TRAIT","text":"greetings","intent":"","topic":"","traits":"","entities":""},{"type":"TRAIT","text":"on/off","intent":"","topic":"","traits":"","entities":""},{"type":"TRAIT","text":"sentiment","intent":"","topic":"","traits":"","entities":""},{"type":"TRAIT","text":"thanks","intent":"","topic":"","traits":"","entities":""},{"type":"ENTITY","text":"who","intent":"","topic":"","traits":"","entities":""},{"type":"ENTITY","text":"age_of_person","intent":"","topic":"","traits":"","entities":""},{"type":"ENTITY","text":"amount_of_money","intent":"","topic":"","traits":"","entities":""},{"type":"ENTITY","text":"contact","intent":"","topic":"","traits":"","entities":""},{"type":"ENTITY","text":"creative_work","intent":"","topic":"","traits":"","entities":""},{"type":"ENTITY","text":"date_time","intent":"","topic":"","traits":"","entities":""},{"type":"ENTITY","text":"distance","intent":"","topic":"","traits":"","entities":""},{"type":"ENTITY","text":"duration","intent":"","topic":"","traits":"","entities":""},{"type":"ENTITY","text":"location","intent":"","topic":"","traits":"","entities":""},{"type":"ENTITY","text":"math_expression","intent":"","topic":"","traits":"","entities":""},{"type":"ENTITY","text":"notable_person","intent":"","topic":"","traits":"","entities":""},{"type":"ENTITY","text":"number","intent":"","topic":"","traits":"","entities":""},{"type":"ENTITY","text":"ordinal","intent":"","topic":"","traits":"","entities":""},{"type":"ENTITY","text":"quantity","intent":"","topic":"","traits":"","entities":""},{"type":"ENTITY","text":"reminder","intent":"","topic":"","traits":"","entities":""},{"type":"ENTITY","text":"temperature","intent":"","topic":"","traits":"","entities":""},{"type":"ENTITY","text":"volume","intent":"","topic":"","traits":"","entities":""},{"type":"STUDENT","text":"Jazmine","intent":"F","topic":"","traits":"ability:5, engagement:5","entities":""},{"type":"STUDENT","text":"Chris","intent":"M","topic":"","traits":"ability:5, engagement:5","entities":""},{"type":"STUDENT","text":"Luis","intent":"M","topic":"","traits":"ability:5, engagement:5","entities":""},{"type":"STUDENT","text":"Oliver","intent":"M","topic":"","traits":"ability:5, engagement:5","entities":""},{"type":"STUDENT","text":"Farrah","intent":"F","topic":"","traits":"ability:5, engagement:5","entities":""},{"type":"INTENT","text":"Giving feedback","intent":"210.2","topic":"Q1","traits":"","entities":""},{"type":"RESPONSE","text":"I just don't know","intent":"100.2","topic":"Q1","traits":"","entities":""},{"type":"REMARK","text":"Why do you think that?","intent":"110.2","topic":"Q2","traits":"","entities":"ask:why,"}]